LICENSE
run_fileserver.py
setup.py
wsgi_fileserver/__init__.py
wsgi_fileserver.egg-info/PKG-INFO
wsgi_fileserver.egg-info/SOURCES.txt
wsgi_fileserver.egg-info/dependency_links.txt
wsgi_fileserver.egg-info/top_level.txt