Metadata-Version: 1.0
Name: wsgi-fileserver
Version: 0.2.8
Summary: WSGI fileserver application
Home-page: http://code.google.com/p/wsgi-fileserver/
Author: OSAF, Mikeal Rogers
Author-email: mikeal.rogers@gmail.com
License: http://www.apache.org/licenses/LICENSE-2.0
Platform: Any
Classifier: Development Status :: 4 - Beta
Classifier: Environment :: Console
Classifier: Intended Audience :: Developers
Classifier: License :: OSI Approved :: Apache Software License
Classifier: Operating System :: OS Independent
Classifier: Topic :: Software Development :: Libraries :: Python Modules
